Metadata-Version: 2.4
Name: pybind11-stubgen
Version: 2.5.4
Summary: PEP 561 type stubs generator for pybind11 modules
Home-page: https://github.com/sizmailov/pybind11-stubgen
Maintainer: Sergei Izmailov
Maintainer-email: sergei.a.izmailov@gmail.com
License: BSD
Requires-Python: ~=3.7
License-File: LICENSE
Dynamic: description
Dynamic: description-content-type
Dynamic: home-page
Dynamic: license
Dynamic: license-file
Dynamic: maintainer
Dynamic: maintainer-email
Dynamic: requires-python
Dynamic: summary
